create_flask_service/GlobalEnum.py
create_flask_service/Service.py
create_flask_service/__init__.py
create_flask_service/template/.env
create_flask_service/template/.gitignore
create_flask_service/template/README.md
create_flask_service/template/__init__.py
create_flask_service/template/app.py
create_flask_service/template/requirements.txt
create_flask_service/template/controller/__init__.py
create_flask_service/template/database/__init__.py
create_flask_service/template/interface/__init__.py
create_flask_service/template/model/__init__.py
create_flask_service/template/schema/__init__.py
create_flask_service/template/scripts/__init__.py
create_flask_service/template/service/__init__.py
create_flask_service/template/utils/__init__.py
create_flask_service-0.1.6.dist-info/LICENSE
create_flask_service-0.1.6.dist-info/METADATA
create_flask_service-0.1.6.dist-info/WHEEL
create_flask_service-0.1.6.dist-info/entry_points.txt
create_flask_service-0.1.6.dist-info/top_level.txt
create_flask_service-0.1.6.dist-info/RECORD
