Metadata-Version: 2.1
Name: create-flask-service
Version: 0.1.6
Summary: Create a Flask microservice with a few keystrokes
Home-page: https://github.com/amickael/create-flask-service
Author: Andrew Mickael
Author-email: andrew.mickael@gmail.com
License: MIT
Platform: NT
Platform: POSIX
Classifier: Programming Language :: Python :: 3
Classifier: License :: OSI Approved :: MIT License
Classifier: Operating System :: MacOS :: MacOS X
Classifier: Operating System :: POSIX
Classifier: Operating System :: Microsoft :: Windows
Classifier: Environment :: Console
Requires-Python: >=3.6
Requires-Dist: halo
Requires-Dist: requests
